[
  {
    "name": "water"
  },
  {
    "name": "salt"
  },
  {
    "name": "sugar"
  },
  {
    "name": "flour"
  },
  {
    "name": "butter"
  },
  {
    "name": "egg"
  },
  {
    "name": "milk"
  },
  {
    "name": "oil"
  },
  {
    "name": "onion"
  },
  {
    "name": "garlic"
  },
  {
    "name": "pepper"
  },
  {
    "name": "rice"
  },
  {
    "name": "tomato"
  },
  {
    "name": "cheese"
  },
  {
    "name": "chicken"
  },
  {
    "name": "beef"
  },
  {
    "name": "pasta"
  },
  {
    "name": "potato"
  },
  {
    "name": "carrot"
  },
  {
    "name": "lettuce"
  },
  {
    "name": "spinach"
  },
  {
    "name": "broccoli"
  },
  {
    "name": "baking powder"
  },
  {
    "name": "honey"
  },
  {
    "name": "lemon"
  },
  {
    "name": "cinnamon"
  },
  {
    "name": "banana"
  },
  {
    "name": "margarine"
  },
  {
    "name": "cornmeal"
  },
  {
    "name": "biscuit dough"
  },
  {
    "name": "walnut"
  },
  {
    "name": "raisins"
  },
  {
    "name": "beer"
  },
  {
    "name": "shortening"
  },
  {
    "name": "lard"
  },
  {
    "name": "yeast"
  },
  {
    "name": "blueberries"
  },
  {
    "name": "chocolate chip"
  },
  {
    "name": "zucchini"
  },
  {
    "name": "apple"
  },
  {
    "name": "vanilla extract"
  },
  {
    "name": "pineapple"
  },
  {
    "name": "buttermilk"
  },
  {
    "name": "baking soda"
  },
  {
    "name": "cream cheese"
  },
  {
    "name": "carrot"
  },
  {
    "name": "turkey"
  },
  {
    "name": "molasses"
  },
  {
    "name": "mayonnaise"
  },
  {
    "name": "syrup"
  },
  {
    "name": "almond"
  },
  {
    "name": "squash"
  },
  {
    "name": "yogurt"
  },
  {
    "name": "wheat"
  },
  {
    "name": "cocoa"
  },
  {
    "name": "pepperoni"
  },
  {
    "name": "rosemary"
  },
  {
    "name": "cranberries"
  },
  {
    "name": "avocado"
  },
  {
    "name": "cucumber"
  },
  {
    "name": "bread"
  },
  {
    "name": "vinegar"
  },
  {
    "name": "ketchup"
  },
  {
    "name": "mustard"
  },
  {
    "name": "mango"
  },
  {
    "name": "strawberry"
  },
  {
    "name": "cilantro"
  },
  {
    "name": "cumin"
  },
  {
    "name": "paprika"
  }
]